trafficgenerator/__init__.py
trafficgenerator/tgn_conftest.py
trafficgenerator/tgn_object.py
trafficgenerator/tgn_server.py
trafficgenerator/tgn_tcl.py
trafficgenerator/tgn_utils.py
trafficgenerator/tgn_vmware.py
pytrafficgen-4.0.1.dist-info/METADATA
pytrafficgen-4.0.1.dist-info/WHEEL
pytrafficgen-4.0.1.dist-info/top_level.txt
pytrafficgen-4.0.1.dist-info/RECORD
